tartan/__init__.py
tartan/cli.py
tartan/tartan.py
tartan-0.1.3.dist-info/AUTHORS.rst
tartan-0.1.3.dist-info/LICENSE
tartan-0.1.3.dist-info/METADATA
tartan-0.1.3.dist-info/WHEEL
tartan-0.1.3.dist-info/entry_points.txt
tartan-0.1.3.dist-info/top_level.txt
tartan-0.1.3.dist-info/RECORD
