Metadata-Version: 2.1
Name: tartan
Version: 0.1.3
Summary: Generates tartan images from threadcount definitions
Home-page: https://github.com/paul-butcher/tartan
Author: Paul Butcher
Author-email: paul.butcher@gmail.com
License: MIT license
Keywords: tartan
Platform: UNKNOWN
Classifier: Development Status :: 4 - Beta
Classifier: Intended Audience :: Developers
Classifier: License :: OSI Approved :: MIT License
Classifier: Natural Language :: English
Classifier: Programming Language :: Python :: 3
Classifier: Programming Language :: Python :: 3.5
Classifier: Programming Language :: Python :: 3.6
Classifier: Programming Language :: Python :: 3.7
Classifier: Programming Language :: Python :: 3.8
Classifier: Topic :: Artistic Software
Requires-Python: >=3.5
Requires-Dist: pillow (==7.0.0)
